wsidicom_data/__init__.py
wsidicom_data/create_encoded_test_files.py
wsidicom_data/data/encoded/Explicit_VR_Big_Endian-GRAYSCALE-16.raw
wsidicom_data/data/encoded/Explicit_VR_Big_Endian-GRAYSCALE-8.raw
wsidicom_data/data/encoded/Explicit_VR_Big_Endian-RGB-8.raw
wsidicom_data/data/encoded/Explicit_VR_Little_Endian-GRAYSCALE-16.raw
wsidicom_data/data/encoded/Explicit_VR_Little_Endian-GRAYSCALE-8.raw
wsidicom_data/data/encoded/Explicit_VR_Little_Endian-RGB-8.raw
wsidicom_data/data/encoded/Implicit_VR_Little_Endian-GRAYSCALE-16.raw
wsidicom_data/data/encoded/Implicit_VR_Little_Endian-GRAYSCALE-8.raw
wsidicom_data/data/encoded/Implicit_VR_Little_Endian-RGB-8.raw
wsidicom_data/data/encoded/JPEG-LS_Lossless_Image_Compression-GRAYSCALE-16.jls
wsidicom_data/data/encoded/JPEG-LS_Lossless_Image_Compression-GRAYSCALE-8.jls
wsidicom_data/data/encoded/JPEG-LS_Lossless_Image_Compression-RGB-8.jls
wsidicom_data/data/encoded/JPEG-LS_Lossy_(Near-Lossless)_Image_Compression-GRAYSCALE-16.jls
wsidicom_data/data/encoded/JPEG-LS_Lossy_(Near-Lossless)_Image_Compression-GRAYSCALE-8.jls
wsidicom_data/data/encoded/JPEG-LS_Lossy_(Near-Lossless)_Image_Compression-RGB-8.jls
wsidicom_data/data/encoded/JPEG_2000_Image_Compression-GRAYSCALE-16.jp2
wsidicom_data/data/encoded/JPEG_2000_Image_Compression-GRAYSCALE-8.jp2
wsidicom_data/data/encoded/JPEG_2000_Image_Compression-RGB-8.jp2
wsidicom_data/data/encoded/JPEG_2000_Image_Compression-YBR-8.jp2
wsidicom_data/data/encoded/JPEG_2000_Image_Compression_(Lossless_Only)-GRAYSCALE-16.jp2
wsidicom_data/data/encoded/JPEG_2000_Image_Compression_(Lossless_Only)-GRAYSCALE-8.jp2
wsidicom_data/data/encoded/JPEG_2000_Image_Compression_(Lossless_Only)-RGB-8.jp2
wsidicom_data/data/encoded/JPEG_2000_Image_Compression_(Lossless_Only)-YBR-8.jp2
wsidicom_data/data/encoded/JPEG_Baseline_(Process_1)-GRAYSCALE-8.jpg
wsidicom_data/data/encoded/JPEG_Baseline_(Process_1)-RGB-8.jpg
wsidicom_data/data/encoded/JPEG_Baseline_(Process_1)-YBR-8.jpg
wsidicom_data-0.3.0.dist-info/METADATA
wsidicom_data-0.3.0.dist-info/WHEEL
wsidicom_data-0.3.0.dist-info/RECORD
