Metadata-Version: 2.1
Name: wsidicom-data
Version: 0.3.0
Summary: Test data for wsidicom
Home-page: https://github.com/imi-bigpicture/wsidicom-data
License: Apache-2.0
Author: Erik O Gabrielsson
Author-email: erik.o.gabrielsson@sectra.com
Requires-Python: >=3.9,<4.0
Classifier: License :: OSI Approved :: Apache Software License
Classifier: Programming Language :: Python :: 3
Classifier: Programming Language :: Python :: 3.9
Classifier: Programming Language :: Python :: 3.10
Classifier: Programming Language :: Python :: 3.11
Provides-Extra: imagecodecs
Provides-Extra: rle
Requires-Dist: imagecodecs (>=2023.9.18,<2024.0.0) ; extra == "imagecodecs"
Requires-Dist: pylibjpeg-rle (>=1.3.0,<2.0.0) ; extra == "rle"
Requires-Dist: wsidicom (>=0.16.0)
Project-URL: Repository, https://github.com/imi-bigpicture/wsidicom-data
